blorb.py
jsgen.py
opcodes.py
zparser.py
z2js-0.2.2.dist-info/licenses/LICENSE
z2js-0.2.2.dist-info/METADATA
z2js-0.2.2.dist-info/WHEEL
z2js-0.2.2.dist-info/entry_points.txt
z2js-0.2.2.dist-info/top_level.txt
z2js-0.2.2.dist-info/RECORD
