Metadata-Version: 2.4
Name: z2js
Version: 0.2.2
Summary: Z-Machine to JavaScript compiler - convert Infocom-style text adventures to playable web games
Author: Aaron Wohl
License-Expression: GPL-3.0-or-later
Project-URL: Homepage, https://github.com/awohl/z2js
Project-URL: Repository, https://github.com/awohl/z2js
Project-URL: Issues, https://github.com/awohl/z2js/issues
Keywords: z-machine,infocom,interactive-fiction,compiler,javascript
Classifier: Development Status :: 4 - Beta
Classifier: Environment :: Console
Classifier: Intended Audience :: Developers
Classifier: Operating System :: OS Independent
Classifier: Programming Language :: Python :: 3
Classifier: Programming Language :: Python :: 3.8
Classifier: Programming Language :: Python :: 3.9
Classifier: Programming Language :: Python :: 3.10
Classifier: Programming Language :: Python :: 3.11
Classifier: Programming Language :: Python :: 3.12
Classifier: Programming Language :: Python :: 3.13
Classifier: Topic :: Games/Entertainment
Classifier: Topic :: Software Development :: Compilers
Requires-Python: >=3.8
License-File: LICENSE
Dynamic: license-file
